fsm_assignment/ques_3/vending_mealy.v
`timescale 1ns / 1ps
module vending_mealy(
 input wire clk,
 input wire rst,
 input wire[1:0]coin,
 output wire dispense,
 output wire chg5
 );
	 reg [1:0] pres_state,next_state;
	 parameter total_0= 0,total_5= 1, total_10=2, total_15= 3;
	 always@(posedge clk)
	 begin
		  if(rst)
				pres_state<= total_0;
		  else
				pres_state=next_state; 
	 end
	 always@(*)
	 begin
		  case(pres_state)
		  total_0: if(coin==0)
						  next_state=total_0;
					  else if(coin==1)
						  next_state=total_5;
					  else
						  next_state=total_10;
		  total_5: if(coin==0)
						  next_state=total_0;
					  else if(coin==1)
						  next_state=total_10;
					  else
						  next_state=total_15;
		  total_10: if(coin==0)
						  next_state=total_0;
					  else if(coin==1)
						  next_state=total_15;
					  else
						  next_state=total_0;
		  total_15: next_state= total_0;
		 endcase
	 end
	 assign dispense= (pres_state==total_10& coin==2'b10) || (pres_state==total_15& coin==2'b01) || (pres_state==total_15& coin==2'b10);
	 assign chg5= (pres_state==total_15& coin==2'b10);
endmodule

fsm_assignment/ques_3/tb_vending_mealy.v
`timescale 1ns / 1ps
module tb_vending_mealy();
	reg clk;
	reg reset;
	reg [1:0] coin;
	wire dispense;
	wire chg5;
	vending_mealy dut (
		.clk(clk),
		.rst(reset),
		.coin(coin),
		.dispense(dispense),
		.chg5(chg5)
	);
	initial clk = 0;
	always #5 clk = ~clk;
		initial begin
			$dumpfile("dump.vcd");
			$dumpvars(0, tb_vending_mealy);
			reset = 1; coin = 2'b00;
			#20; 
			reset = 0;
			@(posedge clk); coin = 2'b01;
			@(posedge clk); coin = 2'b01;
			@(posedge clk); coin = 2'b10;
			@(posedge clk); coin = 2'b00;
			repeat(2) @(posedge clk); coin = 2'b10;
			@(posedge clk); coin = 2'b10;
			@(posedge clk); coin = 2'b01;
			@(posedge clk); coin = 2'b00;
			repeat(2) @(posedge clk); coin = 2'b01;
			@(posedge clk); coin = 2'b00;
			@(posedge clk); coin = 2'b10;
			@(posedge clk); coin = 2'b01;
			@(posedge clk); coin = 2'b10;
			#50;
			$stop;
		end
endmodule

fsm_assignment/ques_3/dump.vcd
$date
	Mon Aug 18 23:57:46 2025
$end
$version
	Icarus Verilog
$end
$timescale
	1ps
$end
$scope module tb_vending_mealy $end
$var wire 1 ! dispense $end
$var wire 1 " chg5 $end
$var reg 1 # clk $end
$var reg 2 $ coin [1:0] $end
$var reg 1 % reset $end
$scope module dut $end
$var wire 1 " chg5 $end
$var wire 1 # clk $end
$var wire 2 & coin [1:0] $end
$var wire 1 ! dispense $end
$var wire 1 % rst $end
$var parameter 32 ' total_0 $end
$var parameter 32 ( total_10 $end
$var parameter 32 ) total_15 $end
$var parameter 32 * total_5 $end
$var reg 2 + next_state [1:0] $end
$var reg 2 , pres_state [1:0] $end
$upscope $end
$upscope $end
$enddefinitions $end
$comment Show the parameter values. $end
$dumpall
b1 *
b11 )
b10 (
b0 '
$end
#0
$dumpvars
bx ,
bx +
b0 &
1%
b0 $
0#
0"
0!
$end
#5000
b0 +
b0 ,
1#
#10000
0#
#15000
1#
#20000
0#
0%
#25000
b1 +
b1 $
b1 &
1#
#30000
0#
#35000
b10 +
b1 ,
1#
#40000
0#
#45000
1!
b0 +
b10 ,
b10 $
b10 &
1#
#50000
0#
#55000
0!
b0 $
b0 &
b0 ,
1#
#60000
0#
#65000
1#
#70000
0#
#75000
b10 +
b10 $
b10 &
1#
#80000
0#
#85000
1!
b0 +
b10 ,
1#
#90000
0#
#95000
0!
b1 +
b1 $
b1 &
b0 ,
1#
#100000
0#
#105000
b0 +
b1 ,
b0 $
b0 &
1#
#110000
0#
#115000
b0 ,
1#
#120000
0#
#125000
b1 +
b1 $
b1 &
1#
#130000
0#
#135000
b0 +
b0 $
b0 &
b1 ,
1#
#140000
0#
#145000
b10 +
b0 ,
b10 $
b10 &
1#
#150000
0#
#155000
b11 +
b1 $
b1 &
b10 ,
1#
#160000
0#
#165000
1!
b0 +
1"
b11 ,
b10 $
b10 &
1#
#170000
0#
#175000
0!
b10 +
0"
b0 ,
1#
#180000
0#
#185000
1!
b0 +
b10 ,
1#
#190000
0#
#195000
0!
b10 +
b0 ,
1#
#200000
0#
#205000
1!
b0 +
b10 ,
1#
